<Properties StartupConfiguration="{57F27184-44E0-4474-9F5A-33272A59B162}|Default">
  <MonoDevelop.Ide.Workbench ActiveDocument="GenCode/Program.cs">
    <Files>
      <File FileName="GenCode/Program.cs" Line="10" Column="2" />
    </Files>
    <Pads>
      <Pad Id="ProjectPad">
        <State name="__root__">
          <Node name="GenCode" expanded="True" selected="True" />
        </State>
      </Pad>
    </Pads>
  </MonoDevelop.Ide.Workbench>
  <MonoDevelop.Ide.DebuggingService.PinnedWatches>
    <Watch file="../../../../../工作/辽阳不动产/IIRS/IIRS/Utilities/AppsettingsUtility.cs" line="38" column="16" endLine="38" endColumn="83" offsetX="-1" offsetY="-1" expression="dbs" liveUpdate="False" />
    <Watch file="../../../../../工作/辽阳不动产/IIRS/IIRS/Utilities/AppsettingsUtility.cs" line="38" column="16" endLine="38" endColumn="83" offsetX="-1" offsetY="-1" expression="dbs" liveUpdate="False" />
  </MonoDevelop.Ide.DebuggingService.PinnedWatches>
  <MonoDevelop.Ide.Workspace ActiveConfiguration="Debug" />
  <MonoDevelop.Ide.ItemProperties.GenCode PreferredExecutionTarget="MonoDevelop.Default" />
  <MonoDevelop.Ide.DebuggingService.Breakpoints>
    <BreakpointStore />
  </MonoDevelop.Ide.DebuggingService.Breakpoints>
  <MultiItemStartupConfigurations />
</Properties>